pytcube/__init__.py
pytcube/logging.py
pytcube/core/__init__.py
pytcube/core/accessor.py
pytcube/core/grid.py
pytcube/core/point.py
pytcube/testing/__init__.py
pytcube/testing/grid.py
pytcube/testing/point.py
pytcube/utils/__init__.py
pytcube/utils/core.py
pytcube/utils/types.py
pytcube-0.0.3.dist-info/METADATA
pytcube-0.0.3.dist-info/WHEEL
pytcube-0.0.3.dist-info/licenses/LICENSE
pytcube-0.0.3.dist-info/RECORD
