Metadata-Version: 2.4
Name: pytcube
Version: 0.0.3
Summary: A Python library for multidimensional subsetting around observation points
Project-URL: Homepage, https://gitlab.ifremer.fr/odatis-public/pytcube
Project-URL: Documentation, https://odatis-public.gitlab-pages.ifremer.fr/pytcube/
Author-email: Gwenaël CAËR <gwenael.caer@data-terra.org>
License:                    GNU LESSER GENERAL PUBLIC LICENSE
License-File: LICENSE
Requires-Python: >=3.11
Requires-Dist: dask
Requires-Dist: fast-vindex>=0.0.2
Requires-Dist: numpy>=1.26
Requires-Dist: pandas>=2.2
Requires-Dist: xarray
Provides-Extra: test
Requires-Dist: pytest-cov>=4.0; extra == 'test'
Requires-Dist: pytest>=7.4; extra == 'test'
